microhorario_dl/__init__.py
microhorario_dl/consultas.py
microhorario_dl/ementa.py
microhorario_dl/exceptions.py
microhorario_dl/models.py
microhorario_dl/parser.py
microhorario_dl/payloads.py
microhorario_dl/utils.py
microhorario_dl-1.6.3.dist-info/LICENSE
microhorario_dl-1.6.3.dist-info/METADATA
microhorario_dl-1.6.3.dist-info/WHEEL
microhorario_dl-1.6.3.dist-info/top_level.txt
microhorario_dl-1.6.3.dist-info/RECORD
