Metadata-Version: 2.1
Name: microhorario-dl
Version: 1.6.3
Summary: PUC-Rio Microhorario Downloader
Home-page: https://github.com/Leinadium/microhorario-dl
Author: Daniel Guimarães <github@Leinadium>
Author-email: daniel.sch.guima@gmail.com
Project-URL: Bug Reports, https://github.com/Leinadium/microhorario-dl/issues
Project-URL: Source, https://github.com/Leinadium/microhorario-dl/
Classifier: Development Status :: 3 - Alpha
Classifier: Programming Language :: Python :: 3
Classifier: License :: OSI Approved :: MIT License
Classifier: Operating System :: OS Independent
Requires-Python: >3.7
License-File: LICENSE
Requires-Dist: beautifulsoup4 >=4
Requires-Dist: requests >=2
